distancemap/__init__.py
distancemap/distancemap.py
distancemap/distances.py
distancemap/functions.py
tests/__init__.py
distance_map-1.0.1.dist-info/LICENSE
distance_map-1.0.1.dist-info/METADATA
distance_map-1.0.1.dist-info/WHEEL
distance_map-1.0.1.dist-info/top_level.txt
distance_map-1.0.1.dist-info/RECORD
