Metadata-Version: 2.1
Name: distance-map
Version: 1.0.1
Summary: Distance Map library
Home-page: https://github.com/Cyril-Meyer/DistanceMap
Author: Cyril Meyer
Author-email: contact@cyrilmeyer.eu
License: UNKNOWN
Platform: UNKNOWN
Classifier: Programming Language :: Python :: 3
Classifier: License :: OSI Approved :: MIT License
Classifier: Operating System :: OS Independent
Requires-Python: >=3.6
Requires-Dist: numpy
Requires-Dist: numba
